backend/__init__.py
backend/build_backend.py
pipebio/__init__.py
pipebio/attachments.py
pipebio/column.py
pipebio/entities.py
pipebio/install_deps.py
pipebio/jobs.py
pipebio/organization_lists.py
pipebio/pipebio_client.py
pipebio/sequences.py
pipebio/shareables.py
pipebio/uploader.py
pipebio/util.py
pipebio/workflows.py
pipebio/annotate/AnnotateForBenchlingParams.py
pipebio/annotate/__init__.py
pipebio/annotate/params.py
pipebio/annotate/service_token_service.py
pipebio/annotate/sort.py
pipebio/annotate/users_service.py
pipebio/models/__init__.py
pipebio/models/attachment_type.py
pipebio/models/entity_types.py
pipebio/models/export_format.py
pipebio/models/field.py
pipebio/models/job_status.py
pipebio/models/job_type.py
pipebio/models/output_link.py
pipebio/models/render_codes.py
pipebio/models/sequence_document_kind.py
pipebio/models/sort.py
pipebio/models/table_column_type.py
pipebio/models/upload_detail.py
pipebio/models/upload_summary.py
pipebio/shared_python/__init__.py
pipebio/shared_python/environment_utils.py
pipebio/shared_python/exceptions.py
pipebio/shared_python/selection_range.py
pipebio/shared_python/util_no_dependencies.py
pipebio-5.0.8.dist-info/licenses/LICENSE
pipebio-5.0.8.dist-info/METADATA
pipebio-5.0.8.dist-info/WHEEL
pipebio-5.0.8.dist-info/top_level.txt
pipebio-5.0.8.dist-info/RECORD
