Metadata-Version: 2.4
Name: pipebio
Version: 5.0.8
Summary: A PipeBio client package
Author-email: PipeBio <support@pipebio.com>
License: BSD 3-clause
Project-URL: Homepage, https://github.com/pipebio/python-library
Classifier: Development Status :: 4 - Beta
Classifier: Intended Audience :: Developers
Classifier: License :: OSI Approved :: BSD License
Classifier: Operating System :: POSIX :: Linux
Classifier: Operating System :: MacOS :: MacOS X
Classifier: Programming Language :: Python :: 3
Classifier: Programming Language :: Python :: 3.8
Classifier: Programming Language :: Python :: 3.9
Classifier: Programming Language :: Python :: 3.10
Classifier: Programming Language :: Python :: 3.11
Classifier: Programming Language :: Python :: 3.12
Classifier: Programming Language :: Python :: 3.13
Requires-Python: <3.14,>=3.8
License-File: LICENSE
Requires-Dist: requests~=2.32.2
Requires-Dist: urllib3<1.27,>=1.26.18; python_version < "3.10"
Requires-Dist: urllib3~=2.4.0; python_version >= "3.10"
Requires-Dist: pandas<3.0.0,>=2.0.0
Requires-Dist: setuptools>=60.0.0
Requires-Dist: biopython~=1.78
Requires-Dist: python-dotenv~=1.0.0; python_version < "3.9"
Requires-Dist: python-dotenv~=1.1.0; python_version >= "3.9"
Requires-Dist: requests-toolbelt~=1.0.0
Requires-Dist: openpyxl~=3.1.5
Requires-Dist: pyarrow<18.0.0,>=10.0.0; python_version < "3.13"
Requires-Dist: pyarrow>=18.0.0; python_version >= "3.13"
Provides-Extra: build
Requires-Dist: build; extra == "build"
Requires-Dist: twine; extra == "build"
Provides-Extra: dev
Requires-Dist: python-dotenv; extra == "dev"
Requires-Dist: pytest; extra == "dev"
Requires-Dist: boto3~=1.35.0; extra == "dev"
Requires-Dist: botocore~=1.35.0; extra == "dev"
Dynamic: license-file
